AUTHORS.rst
CONTRIBUTING.rst
HISTORY.rst
LICENSE
MANIFEST.in
README.rst
setup.cfg
setup.py
docs/Makefile
docs/authors.rst
docs/conf.py
docs/contributing.rst
docs/history.rst
docs/index.rst
docs/installation.rst
docs/make.bat
docs/readme.rst
docs/usage.rst
tests/__init__.py
tests/test_text_file_to_audio.py
text_file_to_audio/__init__.py
text_file_to_audio/cli.py
text_file_to_audio/text_file_to_audio.py
text_to_mp3.egg-info/PKG-INFO
text_to_mp3.egg-info/SOURCES.txt
text_to_mp3.egg-info/dependency_links.txt
text_to_mp3.egg-info/entry_points.txt
text_to_mp3.egg-info/not-zip-safe
text_to_mp3.egg-info/requires.txt
text_to_mp3.egg-info/top_level.txt