Metadata-Version: 1.1
Name: text-to-mp3
Version: 0.1.1
Summary: Converts a text file to mp3
Home-page: https://github.com/shridarpatil/text_file_to_mp3
Author: Shridhar Patil
Author-email: shridharpatil2792@gmail.com
License: MIT license
Download-URL: https://github.com/shridarpatil/text_file_to_mp3/archive/0.1.1.tar.gz
Keywords: text_to_mp3,text to audio,text to mp3
Platform: UNKNOWN
Classifier: Development Status :: 2 - Pre-Alpha
Classifier: Intended Audience :: Developers
Classifier: License :: OSI Approved :: MIT License
Classifier: Natural Language :: English
Classifier: Programming Language :: Python :: 2
Classifier: Programming Language :: Python :: 2.6
Classifier: Programming Language :: Python :: 2.7
Classifier: Programming Language :: Python :: 3
Classifier: Programming Language :: Python :: 3.3
Classifier: Programming Language :: Python :: 3.4
Classifier: Programming Language :: Python :: 3.5
